trace_it/__init__.py
trace_it/config/__init__.py
trace_it/config/context_config.py
trace_it/config/phoenix_tracer.py
trace_it/decorators/__init__.py
trace_it/decorators/embedding_tracer.py
trace_it/decorators/llm_tracer.py
trace_it/decorators/reranking_tracer.py
trace_it/decorators/vector_db_tracer.py
trace_it/middleware/__init__.py
trace_it/middleware/trace_it_middleware.py
trace_it/tracer/__init__.py
trace_it/tracer/phoenix_tracing.py
trace_it-0.1.7.dist-info/LICENSE.txt
trace_it-0.1.7.dist-info/METADATA
trace_it-0.1.7.dist-info/WHEEL
trace_it-0.1.7.dist-info/top_level.txt
trace_it-0.1.7.dist-info/RECORD
