Metadata-Version: 2.1
Name: trace-it
Version: 0.1.7
Summary: A python package for observing traces of your LLM application.
Home-page: https://github.com/Krish-Goyani/Trace_IT
Author: Krish-Goyani
Author-email: krish.goyani@dhiwise.com
License: MIT
Project-URL: Bug Tracker, https://github.com/Krish-Goyani/Trace_IT/issues
Keywords: ai,llm,observability,tracing
Classifier: Development Status :: 5 - Production/Stable
Classifier: Intended Audience :: Developers
Classifier: Topic :: Software Development :: Build Tools
Classifier: License :: OSI Approved :: MIT License
Classifier: Programming Language :: Python
Classifier: Programming Language :: Python :: 3.8
Classifier: Programming Language :: Python :: 3.9
Classifier: Programming Language :: Python :: 3.10
Classifier: Programming Language :: Python :: 3.11
Requires-Python: >=3.8
License-File: LICENSE.txt
Requires-Dist: opentelemetry-api
Requires-Dist: opentelemetry-sdk
Requires-Dist: openinference-semantic-conventions
Requires-Dist: arize-phoenix
Requires-Dist: fastapi
Provides-Extra: testing
Requires-Dist: pytest>=7.1.3; extra == "testing"
Requires-Dist: mypy>=0.971; extra == "testing"
Requires-Dist: flake8>=5.0.4; extra == "testing"
Requires-Dist: tox>=3.25.1; extra == "testing"
Requires-Dist: black>=22.8.0; extra == "testing"
